{"cameraMode":{"drawMode":0,"name":"Shaded","section":"Shading Mode"},"sceneLighting":true,"audioPlay":false,"sceneViewState":{"showFog":true,"showMaterialUpdate":false,"showSkybox":true,"showFlares":true,"showImageEffects":true,"showParticleSystems":true},"in2DMode":false,"pivot":{"x":576.7840576171875,"y":280.0154724121094,"z":-166.84542846679688},"rotation":{"x":0.029392439872026445,"y":-0.010494830086827279,"z":0.00030710705323144794,"w":0.9995179772377014},"size":445.1751403808594,"orthographic":false}